[{"email":"nulla.ante@vestibul.co.uk","id":"AeHIrLTr6JkxGE6SN-0Rw","name":"Allen Raymond","phone":"(992) 914-3792"},{"email":"dui.in@egetlacus.ca","id":"qdggE76Jtbfd9eWJHrssH","name":"Chaim Lewis","phone":"(294) 840-6685"},{"email":"mattis.Cras@nonenimMauris.net","id":"drsAJ4SHPYqZeG-83QTVW","name":"Kennedy Lane","phone":"(542) 451-7038"},{"email":"est@utquamvel.net","id":"vza2RIzNGIwutCVCs4mCL","name":"Wylie Pope","phone":"(692) 802-2949"},{"email":"nibh@semsempererat.com","id":"05olLMgyVQdWRwgKfg5J6","name":"Cyrus Jackson","phone":"(501) 472-5218"},{"email":"scelerisque@magnis.org","id":"1DEXoP8AuCGYc1YgoQ6hw","name":"Abbot Franks","phone":"(186) 568-3720"},{"email":"pharetra.ut@dictum.co.uk","id":"Z5sbDlS7pCzNsnAHLtDJd","name":"Reuben Henry","phone":"(715) 598-5792"},{"email":"dui.Fusce.diam@Donec.com","id":"C9sjBfCo4UJCWjzBnOtxl","name":"Simon Morton","phone":"(233) 738-2360"},{"email":"nec@Nulla.com","id":"e6ywwRe4jcqxXfCZOj_1e","name":"Thomas Lucas","phone":"(704) 398-7993"},{"email":"Donec.elementum@scelerisquescelerisquedui.net","id":"rsKkOQUi80UsgVPCcLZZW","name":"Alec Howard","phone":"(748) 206-2688"},{"name":"Igor","email":"any@any.gmail.com","phone":"e6ywwRe4jcqxXfCZOj_1e","id":"52BVHwRrR"},{"name":"Igor","email":"any@any.gmail.com","phone":"e6ywwRe4jcqxXfCZOj_1e","id":"0b2ManXf8"},{"name":"Igor","email":"any@any.gmail.com","phone":"e6ywwRe4jcqxXfCZOj_1e","id":"CtHgee-MU"},{"name":"Igor","email":"any@any.gmail.com","phone":"e6ywwRe4jcqxXfCZOj_1e","id":"hbuLyur3r"},{"name":"Igor","email":"any@any.gmail.com","phone":"e6ywwRe4jcqxXfCZOj_1e","id":"SY5AmJtxs"},{"name":"Igor","email":"any@any.gmail.com","phone":"e6ywwRe4jcqxXfCZOj_1e","id":"IisXpPgSl"},{"name":"Igor","email":"any@any.gmail.com","phone":"e6ywwRe4jcqxXfCZOj_1e","id":"Qyoqfcazr"},{"name":"Igor","email":"any@any.gmail.com","phone":"e6ywwRe4jcqxXfCZOj_1e","id":"N6J08gGnu"},{"name":"Igor","email":"any@any.gmail.com","phone":"e6ywwRe4jcqxXfCZOj_1e","id":"7QnGtfirl"},{"name":"Igor","email":"any@any.gmail.com","phone":"e6ywwRe4jcqxXfCZOj_1e","id":"PXq7Rbe4E"},{"name":"Igor","email":"any@any.gmail.com","phone":"e6ywwRe4jcqxXfCZOj_1e","id":"yeHI-i5bJ"},{"name":"Igor","email":"any@any.gmail.com","phone":"e6ywwRe4jcqxXfCZOj_1e","id":"5S1tJxY5C"},{"name":"Igor","email":"any@any.gmail.com","phone":"e6ywwRe4jcqxXfCZOj_1e","id":"hfKa78tVv"},{"name":"Igor","email":"any@any.gmail.com","phone":"e6ywwRe4jcqxXfCZOj_1e","id":"5xloaWpfL"},{"name":"Igor","email":"any@any.gmail.com","phone":"e6ywwRe4jcqxXfCZOj_1e","id":"AH89C1ZKG"},{"name":"Igor","email":"any@any.gmail.com","phone":"e6ywwRe4jcqxXfCZOj_1e","id":"J36nfaRmJ"},{"name":"Igor","email":"any@any.gmail.com","phone":"e6ywwRe4jcqxXfCZOj_1e","id":"eTSXzH0aB"},{"name":"Igor","email":"any@any.gmail.com","phone":"e6ywwRe4jcqxXfCZOj_1e","id":"sBCqZJFtk"},{"name":"Igor","email":"any@any.gmail.com","phone":"e6ywwRe4jcqxXfCZOj_1e","id":"TaXjtAcRK"},{"name":"Igor","email":"any@any.gmail.com","phone":"e6ywwRe4jcqxXfCZOj_1e","id":"DAlaTvnB3"},{"name":"Igor","email":"any@any.gmail.com","phone":"e6ywwRe4jcqxXfCZOj_1e","id":"Vo8BCk78k"},{"name":"Igor","email":"any@any.gmail.com","phone":"e6ywwRe4jcqxXfCZOj_1e","id":"Vci0Y_r_8"},{"name":"Igor","email":"any@any.gmail.com","phone":"e6ywwRe4jcqxXfCZOj_1e","id":"FJSP8PdLd"},{"name":"Igor","email":"any@any.gmail.com","phone":"e6ywwRe4jcqxXfCZOj_1e","id":"vSN_Q8dq8"},{"name":"Igor","email":"any@any.gmail.com","phone":"e6ywwRe4jcqxXfCZOj_1e","id":"dU2wdwlSs"},{"name":"Igor","email":"any@any.gmail.com","phone":"e6ywwRe4jcqxXfCZOj_1e","id":"oJ1rhkB4p"},{"name":"Igor","email":"any@any.gmail.com","phone":"e6ywwRe4jcqxXfCZOj_1e","id":"88LSWbyzG"},{"name":"Igor","email":"any@any.gmail.com","phone":"e6ywwRe4jcqxXfCZOj_1e","id":"CH9ow_Z9c"},{"name":"Igor","email":"any@any.gmail.com","phone":"e6ywwRe4jcqxXfCZOj_1e","id":"YbTyX1maw"},{"name":"Igor","email":"any@any.gmail.com","phone":"e6ywwRe4jcqxXfCZOj_1e","id":"XYu5nXFnC"},{"name":"Igor","email":"any@any.gmail.com","phone":"e6ywwRe4jcqxXfCZOj_1e","id":"hNOWWvtTP"},{"name":"Igor","email":"any@any.gmail.com","phone":"e6ywwRe4jcqxXfCZOj_1e","id":"pOIMM2xPQ"},{"name":"Igor","email":"any@any.gmail.com","phone":"e6ywwRe4jcqxXfCZOj_1e","id":"1ztDpAowA"},{"name":"Igor","email":"any@any.gmail.com","phone":"e6ywwRe4jcqxXfCZOj_1e","id":"UorZBTXHv"},{"name":"Igor","email":"any@any.gmail.com","phone":"e6ywwRe4jcqxXfCZOj_1e","id":"M4yWC9eZ7"},{"name":"Igor","email":"any@any.gmail.com","phone":"e6ywwRe4jcqxXfCZOj_1e","id":"JZEKrL7Tc"},{"name":"Igor","email":"any@any.gmail.com","phone":"e6ywwRe4jcqxXfCZOj_1e","id":"igFBl7p97"},{"name":"Igor","email":"any@any.gmail.com","phone":"e6ywwRe4jcqxXfCZOj_1e","id":"EZxWx9tdj"},{"name":"Igor","email":"any@any.gmail.com","phone":"e6ywwRe4jcqxXfCZOj_1e","id":"IQTL6l23x"},{"name":"Igor","email":"any@any.gmail.com","phone":"e6ywwRe4jcqxXfCZOj_1e","id":"FW3-n2Dkm"},{"name":"Igor","email":"any@any.gmail.com","phone":"e6ywwRe4jcqxXfCZOj_1e","id":"BpfQSyAnm"},{"name":"Igor","email":"any@any.gmail.com","phone":"e6ywwRe4jcqxXfCZOj_1e","id":"QWt1QwJiD"},{"name":"Igor","email":"any@any.gmail.com","phone":"e6ywwRe4jcqxXfCZOj_1e","id":"MQNGMfcXW"},{"name":"Igor","email":"any@any.gmail.com","phone":"e6ywwRe4jcqxXfCZOj_1e","id":"f5e9Q-HUY"},{"name":"Igor","email":"any@any.gmail.com","phone":"e6ywwRe4jcqxXfCZOj_1e","id":"DCKHFKgqe"},{"name":"Igor","email":"any@any.gmail.com","phone":"e6ywwRe4jcqxXfCZOj_1e","id":"Ke_klX6FL"},{"name":"Igor","email":"any@any.gmail.com","phone":"e6ywwRe4jcqxXfCZOj_1e","id":"Rm_0RzoV1"},{"name":"Igor","email":"any@any.gmail.com","phone":"e6ywwRe4jcqxXfCZOj_1e","id":"jpnJBjUMJ"},{"name":"Igor","email":"any@any.gmail.com","phone":"e6ywwRe4jcqxXfCZOj_1e","id":"fl_NTyp4c"},{"name":"Igor","email":"any@any.gmail.com","phone":"e6ywwRe4jcqxXfCZOj_1e","id":"3G71bwe9Z"},{"name":"Igor","email":"any@any.gmail.com","phone":"e6ywwRe4jcqxXfCZOj_1e","id":"LdXMpfMae"},{"name":"Igor","email":"any@any.gmail.com","phone":"e6ywwRe4jcqxXfCZOj_1e","id":"elHzfKg57"},{"name":"Igor","email":"any@any.gmail.com","phone":"e6ywwRe4jcqxXfCZOj_1e","id":"870uKHXWh"},{"name":"Igor","email":"any@any.gmail.com","phone":"e6ywwRe4jcqxXfCZOj_1e","id":"jpqgNOlUR"},{"name":"Igor","email":"any@any.gmail.com","phone":"e6ywwRe4jcqxXfCZOj_1e","id":"LESBUalio"},{"name":"Igor","email":"any@any.gmail.com","phone":"e6ywwRe4jcqxXfCZOj_1e","id":"KHyMdpToO"},{"name":"Igor","email":"any@any.gmail.com","phone":"e6ywwRe4jcqxXfCZOj_1e","id":"TdR_SL0Pq"},{"name":"Igor","email":"any@any.gmail.com","phone":"e6ywwRe4jcqxXfCZOj_1e","id":"Oqu3Pqwd7"},{"name":"Igor","email":"any@any.gmail.com","phone":"e6ywwRe4jcqxXfCZOj_1e","id":"ZZvYWBrcR"},{"name":"Igor","email":"any@any.gmail.com","phone":"e6ywwRe4jcqxXfCZOj_1e","id":"1BhYCaVtf"},{"name":"Igor","email":"any@any.gmail.com","phone":"e6ywwRe4jcqxXfCZOj_1e","id":"vAdqvjFCY"},{"name":"Igor","email":"any@any.gmail.com","phone":"e6ywwRe4jcqxXfCZOj_1e","id":"ofiynQcU3"},{"name":"Igor","email":"any@any.gmail.com","phone":"e6ywwRe4jcqxXfCZOj_1e","id":"LMEB6GZmT"},{"name":"Igor","email":"any@any.gmail.com","phone":"e6ywwRe4jcqxXfCZOj_1e","id":"Rc2j9Xvaw"},{"name":"Igor","email":"any@any.gmail.com","phone":"e6ywwRe4jcqxXfCZOj_1e","id":"X8BX2p5q_"},{"name":"Igor","email":"any@any.gmail.com","phone":"e6ywwRe4jcqxXfCZOj_1e","id":"SP8OmFfWt"},{"name":"Igor","email":"any@any.gmail.com","phone":"e6ywwRe4jcqxXfCZOj_1e","id":"3IeXonQv3"},{"name":"Igor","email":"any@any.gmail.com","phone":"e6ywwRe4jcqxXfCZOj_1e","id":"y1a9hz030"},{"name":"Igor","email":"any@any.gmail.com","phone":"e6ywwRe4jcqxXfCZOj_1e","id":"v5KnhnrWV"},{"name":"Igor","email":"any@any.gmail.com","phone":"e6ywwRe4jcqxXfCZOj_1e","id":"R5ptlNSAi"},{"name":"Igor","email":"any@any.gmail.com","phone":"e6ywwRe4jcqxXfCZOj_1e","id":"iyATpsLcn"},{"name":"Igor","email":"any@any.gmail.com","phone":"e6ywwRe4jcqxXfCZOj_1e","id":"VV15pd6s7"},{"name":"Igor","email":"any@any.gmail.com","phone":"e6ywwRe4jcqxXfCZOj_1e","id":"Zdvaa4c1S"},{"name":"Igor","email":"any@any.gmail.com","phone":"e6ywwRe4jcqxXfCZOj_1e","id":"dabLxGyb9"},{"name":"Igor","email":"any@any.gmail.com","phone":"e6ywwRe4jcqxXfCZOj_1e","id":"uQ_he_Da8"},{"name":"Igor","email":"any@any.gmail.com","phone":"e6ywwRe4jcqxXfCZOj_1e","id":"A5sgSmejX"},{"name":"Igor","email":"any@any.gmail.com","phone":"e6ywwRe4jcqxXfCZOj_1e","id":"fW8jZQyNF"},{"name":"Igor","email":"any@any.gmail.com","phone":"e6ywwRe4jcqxXfCZOj_1e","id":"hMbjpd3KC"},{"name":"Igor","email":"any@any.gmail.com","phone":"e6ywwRe4jcqxXfCZOj_1e","id":"PESsYor8h"},{"name":"Igor","email":"any@any.gmail.com","phone":"e6ywwRe4jcqxXfCZOj_1e","id":"7j5_WJtOK"},{"name":"Igor","email":"any@any.gmail.com","phone":"e6ywwRe4jcqxXfCZOj_1e","id":"BQP0NYgnC"},{"name":"Igor","email":"any@any.gmail.com","phone":"e6ywwRe4jcqxXfCZOj_1e","id":"TFatDZJ0o"},{"name":"Igor","email":"any@any.gmail.com","phone":"e6ywwRe4jcqxXfCZOj_1e","id":"udE5MoTyU"},{"name":"Igor","email":"any@any.gmail.com","phone":"e6ywwRe4jcqxXfCZOj_1e","id":"yFDS1fVCC"},{"name":"Igor","email":"any@any.gmail.com","phone":"e6ywwRe4jcqxXfCZOj_1e","id":"dNAARNPyK"},{"name":"Igor","email":"any@any.gmail.com","phone":"e6ywwRe4jcqxXfCZOj_1e","id":"tfWl-gVFW"},{"name":"Igor","email":"any@any.gmail.com","phone":"e6ywwRe4jcqxXfCZOj_1e","id":"oc2nFRIO1"},{"name":"Igor","email":"any@any.gmail.com","phone":"e6ywwRe4jcqxXfCZOj_1e","id":"5-59I7a7g"},{"name":"Igor","email":"any@any.gmail.com","phone":"e6ywwRe4jcqxXfCZOj_1e","id":"mRgYOPe65"},{"name":"Igor","email":"any@any.gmail.com","phone":"e6ywwRe4jcqxXfCZOj_1e","id":"FCaXLe_Vd"},{"name":"Igor","email":"any@any.gmail.com","phone":"e6ywwRe4jcqxXfCZOj_1e","id":"zxEGokIgk"},{"name":"Igor","email":"any@any.gmail.com","phone":"e6ywwRe4jcqxXfCZOj_1e","id":"vo30wKTw5"},{"name":"Igor","email":"any@any.gmail.com","phone":"e6ywwRe4jcqxXfCZOj_1e","id":"OpQbPH90E"},{"name":"Igor","email":"any@any.gmail.com","phone":"e6ywwRe4jcqxXfCZOj_1e","id":"ZRVEmy9Zk"},{"name":"Igor","email":"any@any.gmail.com","phone":"e6ywwRe4jcqxXfCZOj_1e","id":"j7wA0X1Px"},{"name":"Igor","email":"any@any.gmail.com","phone":"e6ywwRe4jcqxXfCZOj_1e","id":"sM8e13sQv"},{"name":"Igor","email":"any@any.gmail.com","phone":"e6ywwRe4jcqxXfCZOj_1e","id":"WESAng0Od"},{"name":"Igor","email":"any@any.gmail.com","phone":"e6ywwRe4jcqxXfCZOj_1e","id":"LAvXKwWA_"},{"name":"Igor","email":"any@any.gmail.com","phone":"e6ywwRe4jcqxXfCZOj_1e","id":"Af0OFtqmb"},{"name":"Igor","email":"any@any.gmail.com","phone":"e6ywwRe4jcqxXfCZOj_1e","id":"QuUuXsZiY"},{"name":"Igor","email":"any@any.gmail.com","phone":"e6ywwRe4jcqxXfCZOj_1e","id":"E2RZqPlnR"},{"name":"Igor","email":"any@any.gmail.com","phone":"e6ywwRe4jcqxXfCZOj_1e","id":"1jrWNZ56u"},{"name":"Igor","email":"any@any.gmail.com","phone":"e6ywwRe4jcqxXfCZOj_1e","id":"dfbuhI8tr"},{"name":"Igor","email":"any@any.gmail.com","phone":"e6ywwRe4jcqxXfCZOj_1e","id":"sJCCf4wWs"},{"name":"Igor","email":"any@any.gmail.com","phone":"e6ywwRe4jcqxXfCZOj_1e","id":"Dfb71Zy7c"},{"name":"Igor","email":"any@any.gmail.com","phone":"e6ywwRe4jcqxXfCZOj_1e","id":"CaFrLSkmR"},{"name":"Igor","email":"any@any.gmail.com","phone":"e6ywwRe4jcqxXfCZOj_1e","id":"hS7VqqNQT"},{"name":"Igor","email":"any@any.gmail.com","phone":"e6ywwRe4jcqxXfCZOj_1e","id":"rIldyiLlZ"},{"name":"Igor","email":"any@any.gmail.com","phone":"e6ywwRe4jcqxXfCZOj_1e","id":"rsYl181GI"},{"name":"Igor","email":"any@any.gmail.com","phone":"e6ywwRe4jcqxXfCZOj_1e","id":"YwvwEkuJ8"},{"name":"Igor","email":"any@any.gmail.com","phone":"e6ywwRe4jcqxXfCZOj_1e","id":"9dZMBBS7g"},{"name":"Igor","email":"any@any.gmail.com","phone":"e6ywwRe4jcqxXfCZOj_1e","id":"NTwswQbg2"},{"name":"Igor","email":"any@any.gmail.com","phone":"e6ywwRe4jcqxXfCZOj_1e","id":"2rfiU9wt7"},{"name":"Igor","email":"any@any.gmail.com","phone":"e6ywwRe4jcqxXfCZOj_1e","id":"wE9TSu9nt"},{"name":"Igor","email":"any@any.gmail.com","phone":"e6ywwRe4jcqxXfCZOj_1e","id":"RKVCVU2Ff"},{"name":"Igor","email":"any@any.gmail.com","phone":"e6ywwRe4jcqxXfCZOj_1e","id":"5R1evyoGk"},{"name":"Igor","email":"any@any.gmail.com","phone":"e6ywwRe4jcqxXfCZOj_1e","id":"-tq3JfZx6"},{"name":"Igor","email":"any@any.gmail.com","phone":"e6ywwRe4jcqxXfCZOj_1e","id":"6PsbRJpBa"},{"name":"Igor","email":"any@any.gmail.com","phone":"e6ywwRe4jcqxXfCZOj_1e","id":"pic6FqVfl"},{"name":"Igor","email":"any@any.gmail.com","phone":"e6ywwRe4jcqxXfCZOj_1e","id":"R6Vi-i9fB"},{"name":"Igor","email":"any@any.gmail.com","phone":"e6ywwRe4jcqxXfCZOj_1e","id":"usSa4v5pc"},{"name":"Igor","email":"any@any.gmail.com","phone":"e6ywwRe4jcqxXfCZOj_1e","id":"ATuuOp_VK"},{"name":"Igor","email":"any@any.gmail.com","phone":"e6ywwRe4jcqxXfCZOj_1e","id":"TKHDcGZsk"},{"name":"Igor","email":"any@any.gmail.com","phone":"e6ywwRe4jcqxXfCZOj_1e","id":"dnvskw2WW"},{"name":"Igor","email":"any@any.gmail.com","phone":"e6ywwRe4jcqxXfCZOj_1e","id":"-08TTp9X6"},{"name":"Igor","email":"any@any.gmail.com","phone":"e6ywwRe4jcqxXfCZOj_1e","id":"ht4DsZwlG"},{"name":"Igor","email":"any@any.gmail.com","phone":"e6ywwRe4jcqxXfCZOj_1e","id":"4O4oqAMuA"},{"name":"Igor","email":"any@any.gmail.com","phone":"e6ywwRe4jcqxXfCZOj_1e","id":"jN9K3Hcj8"},{"name":"Igor","email":"any@any.gmail.com","phone":"e6ywwRe4jcqxXfCZOj_1e","id":"6_UPgJ0mM"},{"name":"Igor","email":"any@any.gmail.com","phone":"e6ywwRe4jcqxXfCZOj_1e","id":"h1ZzAje_x"},{"name":"Igor","email":"any@any.gmail.com","phone":"e6ywwRe4jcqxXfCZOj_1e","id":"kOBDjX3Y1"},{"name":"Igor","email":"any@any.gmail.com","phone":"e6ywwRe4jcqxXfCZOj_1e","id":"nIVpYvSCe"},{"name":"Igor","email":"any@any.gmail.com","phone":"e6ywwRe4jcqxXfCZOj_1e","id":"5PdjQwWEG"},{"name":"Igor","email":"any@any.gmail.com","phone":"e6ywwRe4jcqxXfCZOj_1e","id":"kD8OeuYbz"},{"name":"Igor","email":"any@any.gmail.com","phone":"e6ywwRe4jcqxXfCZOj_1e","id":"h3yAParTi"},{"name":"Igor","email":"any@any.gmail.com","phone":"e6ywwRe4jcqxXfCZOj_1e","id":"pUcO6L2-E"},{"name":"Igor","email":"any@any.gmail.com","phone":"e6ywwRe4jcqxXfCZOj_1e","id":"mJlsp2Kee"},{"name":"Igor","email":"any@any.gmail.com","phone":"e6ywwRe4jcqxXfCZOj_1e","id":"P41aUZpMv"},{"name":"Igor","email":"any@any.gmail.com","phone":"e6ywwRe4jcqxXfCZOj_1e","id":"TmNKh15Yz"},{"name":"Igor","email":"any@any.gmail.com","phone":"e6ywwRe4jcqxXfCZOj_1e","id":"nGzh_Yc-q"},{"name":"Igor","email":"any@any.gmail.com","phone":"e6ywwRe4jcqxXfCZOj_1e","id":"UT35w93a5"},{"name":"Igor","email":"any@any.gmail.com","phone":"e6ywwRe4jcqxXfCZOj_1e","id":"QZkRqo2Th"},{"name":"Igor","email":"any@any.gmail.com","phone":"e6ywwRe4jcqxXfCZOj_1e","id":"t-TEgGnhp"},{"name":"Igor","email":"any@any.gmail.com","phone":"e6ywwRe4jcqxXfCZOj_1e","id":"JdkuAkwTa"},{"name":"Igor","email":"any@any.gmail.com","phone":"e6ywwRe4jcqxXfCZOj_1e","id":"o_Ip7s7l4"},{"name":"Igor","email":"any@any.gmail.com","phone":"e6ywwRe4jcqxXfCZOj_1e","id":"GJIIFDVX5"},{"name":"Igor","email":"any@any.gmail.com","phone":"e6ywwRe4jcqxXfCZOj_1e","id":"cOezIcnS6"},{"name":"Igor","email":"any@any.gmail.com","phone":"e6ywwRe4jcqxXfCZOj_1e","id":"FeBcaSNAF"},{"name":"Igor","email":"any@any.gmail.com","phone":"e6ywwRe4jcqxXfCZOj_1e","id":"c-mFaWNcU"},{"name":"Igor","email":"any@any.gmail.com","phone":"e6ywwRe4jcqxXfCZOj_1e","id":"6MMYEiZcj"},{"name":"Igor","email":"any@any.gmail.com","phone":"e6ywwRe4jcqxXfCZOj_1e","id":"UTeAHYYH3"},{"name":"Igor","email":"any@any.gmail.com","phone":"e6ywwRe4jcqxXfCZOj_1e","id":"BnHjlXjuu"},{"name":"Igor","email":"any@any.gmail.com","phone":"e6ywwRe4jcqxXfCZOj_1e","id":"Jhp2bYHhG"},{"name":"Igor","email":"any@any.gmail.com","phone":"e6ywwRe4jcqxXfCZOj_1e","id":"qUoOyn6B2"},{"name":"Igor","email":"any@any.gmail.com","phone":"e6ywwRe4jcqxXfCZOj_1e","id":"ZTUBmDbOL"},{"name":"Igor","email":"any@any.gmail.com","phone":"e6ywwRe4jcqxXfCZOj_1e","id":"sbG9VXPMs"},{"name":"Igor","email":"any@any.gmail.com","phone":"e6ywwRe4jcqxXfCZOj_1e","id":"FLKnM7hYw"},{"name":"Igor","email":"any@any.gmail.com","phone":"e6ywwRe4jcqxXfCZOj_1e","id":"WhA9uuTxP"},{"name":"Igor","email":"any@any.gmail.com","phone":"e6ywwRe4jcqxXfCZOj_1e","id":"1dxWHJ0Uz"},{"name":"Igor","email":"any@any.gmail.com","phone":"e6ywwRe4jcqxXfCZOj_1e","id":"sgvHKA7Z_"},{"name":"Igor","email":"any@any.gmail.com","phone":"e6ywwRe4jcqxXfCZOj_1e","id":"WtOcqH5iC"},{"name":"Igor","email":"any@any.gmail.com","phone":"e6ywwRe4jcqxXfCZOj_1e","id":"1G-hUgh8m"},{"name":"Igor","email":"any@any.gmail.com","phone":"e6ywwRe4jcqxXfCZOj_1e","id":"TRz7-FlPO"},{"name":"Igor","email":"any@any.gmail.com","phone":"e6ywwRe4jcqxXfCZOj_1e","id":"jL3ibghbZ"},{"name":"Igor","email":"any@any.gmail.com","phone":"e6ywwRe4jcqxXfCZOj_1e","id":"_Dhv-yiLy"},{"name":"Igor","email":"any@any.gmail.com","phone":"e6ywwRe4jcqxXfCZOj_1e","id":"5sm51pSn2"},{"name":"Igor","email":"any@any.gmail.com","phone":"e6ywwRe4jcqxXfCZOj_1e","id":"HrTH4jXWB"},{"name":"Igor","email":"any@any.gmail.com","phone":"e6ywwRe4jcqxXfCZOj_1e","id":"GWoUofMll"},{"name":"Igor","email":"any@any.gmail.com","phone":"e6ywwRe4jcqxXfCZOj_1e","id":"R57qSwp6f"},{"name":"Igor","email":"any@any.gmail.com","phone":"e6ywwRe4jcqxXfCZOj_1e","id":"CGALJDN4J"},{"name":"Igor","email":"any@any.gmail.com","phone":"e6ywwRe4jcqxXfCZOj_1e","id":"vd7U9qdve"},{"name":"Igor","email":"any@any.gmail.com","phone":"e6ywwRe4jcqxXfCZOj_1e","id":"HG_q34WeA"},{"name":"Igor","email":"any@any.gmail.com","phone":"e6ywwRe4jcqxXfCZOj_1e","id":"SI4fd6csS"},{"name":"Igor","email":"any@any.gmail.com","phone":"e6ywwRe4jcqxXfCZOj_1e","id":"4m5tnAHf6"},{"name":"Igor","email":"any@any.gmail.com","phone":"e6ywwRe4jcqxXfCZOj_1e","id":"im8x_MAIB"},{"name":"Igor","email":"any@any.gmail.com","phone":"e6ywwRe4jcqxXfCZOj_1e","id":"GduErMUOd"},{"name":"Igor","email":"any@any.gmail.com","phone":"e6ywwRe4jcqxXfCZOj_1e","id":"sSu9HWtLy"},{"name":"Igor","email":"any@any.gmail.com","phone":"e6ywwRe4jcqxXfCZOj_1e","id":"LqCTNaRgx"},{"name":"Igor","email":"any@any.gmail.com","phone":"e6ywwRe4jcqxXfCZOj_1e","id":"HRLqa5uRc"},{"name":"Igor","email":"any@any.gmail.com","phone":"e6ywwRe4jcqxXfCZOj_1e","id":"av4tINLqA"},{"name":"Igor","email":"any@any.gmail.com","phone":"e6ywwRe4jcqxXfCZOj_1e","id":"GvQuYy1Ar"},{"name":"Igor","email":"any@any.gmail.com","phone":"e6ywwRe4jcqxXfCZOj_1e","id":"wnmghG08e"},{"name":"Igor","email":"any@any.gmail.com","phone":"e6ywwRe4jcqxXfCZOj_1e","id":"WIS-Fzi36"},{"name":"Igor","email":"any@any.gmail.com","phone":"e6ywwRe4jcqxXfCZOj_1e","id":"Yto3ID46T"},{"name":"Igor","email":"any@any.gmail.com","phone":"e6ywwRe4jcqxXfCZOj_1e","id":"N6SS99Up2"},{"name":"Igor","email":"any@any.gmail.com","phone":"e6ywwRe4jcqxXfCZOj_1e","id":"DAJ_Cva1T"},{"name":"Igor","email":"any@any.gmail.com","phone":"e6ywwRe4jcqxXfCZOj_1e","id":"UWPEYhy_r"},{"name":"Igor","email":"any@any.gmail.com","phone":"e6ywwRe4jcqxXfCZOj_1e","id":"0tXmEwFlA"},{"name":"Igor","email":"any@any.gmail.com","phone":"e6ywwRe4jcqxXfCZOj_1e","id":"9P_bnNx2I"},{"name":"Igor","email":"any@any.gmail.com","phone":"e6ywwRe4jcqxXfCZOj_1e","id":"MQsp7veN4"},{"name":"Igor","email":"any@any.gmail.com","phone":"e6ywwRe4jcqxXfCZOj_1e","id":"xwH8wJAU5"},{"name":"Igor","email":"any@any.gmail.com","phone":"e6ywwRe4jcqxXfCZOj_1e","id":"KNLNvZin7"},{"name":"Igor","email":"any@any.gmail.com","phone":"e6ywwRe4jcqxXfCZOj_1e","id":"Lw1jrC5IK"},{"name":"Igor","email":"any@any.gmail.com","phone":"e6ywwRe4jcqxXfCZOj_1e","id":"vy0LlcfKy"},{"name":"Igor","email":"any@any.gmail.com","phone":"e6ywwRe4jcqxXfCZOj_1e","id":"3dgI_LrTk"},{"name":"Igor","email":"any@any.gmail.com","phone":"e6ywwRe4jcqxXfCZOj_1e","id":"TYM2Kc_Ht"},{"name":"Igor","email":"any@any.gmail.com","phone":"e6ywwRe4jcqxXfCZOj_1e","id":"bX_jZGWqu"},{"name":"Igor","email":"any@any.gmail.com","phone":"e6ywwRe4jcqxXfCZOj_1e","id":"ZJ0B0RoLZ"},{"name":"Igor","email":"any@any.gmail.com","phone":"e6ywwRe4jcqxXfCZOj_1e","id":"Zi_s5QSli"},{"name":"Igor","email":"any@any.gmail.com","phone":"e6ywwRe4jcqxXfCZOj_1e","id":"cN-CfyI-8"},{"name":"Igor","email":"any@any.gmail.com","phone":"e6ywwRe4jcqxXfCZOj_1e","id":"IXrdDUR81"},{"name":"Igor","email":"any@any.gmail.com","phone":"e6ywwRe4jcqxXfCZOj_1e","id":"BidXi2ymM"},{"name":"Igor","email":"any@any.gmail.com","phone":"e6ywwRe4jcqxXfCZOj_1e","id":"-23E4uAe1"},{"name":"Igor","email":"any@any.gmail.com","phone":"e6ywwRe4jcqxXfCZOj_1e","id":"sUcSZx4bx"},{"name":"Igor","email":"any@any.gmail.com","phone":"e6ywwRe4jcqxXfCZOj_1e","id":"UEyVa-0ed"},{"name":"Igor","email":"any@any.gmail.com","phone":"e6ywwRe4jcqxXfCZOj_1e","id":"O-i71HF1G"},{"name":"Igor","email":"any@any.gmail.com","phone":"e6ywwRe4jcqxXfCZOj_1e","id":"gslrIHDq9"},{"name":"Igor","email":"any@any.gmail.com","phone":"e6ywwRe4jcqxXfCZOj_1e","id":"UAFtxG4SS"},{"name":"Igor","email":"any@any.gmail.com","phone":"e6ywwRe4jcqxXfCZOj_1e","id":"TtAtZLgNU"},{"name":"Igor","email":"any@any.gmail.com","phone":"e6ywwRe4jcqxXfCZOj_1e","id":"0k_oVKqny"},{"name":"Igor","email":"any@any.gmail.com","phone":"e6ywwRe4jcqxXfCZOj_1e","id":"A-M9euu-V"},{"name":"Igor","email":"any@any.gmail.com","phone":"e6ywwRe4jcqxXfCZOj_1e","id":"3k07p6pav"},{"name":"Igor","email":"any@any.gmail.com","phone":"e6ywwRe4jcqxXfCZOj_1e","id":"noc0pnOeF"},{"name":"Igor","email":"any@any.gmail.com","phone":"e6ywwRe4jcqxXfCZOj_1e","id":"PpyXP0WYs"},{"name":"Igor","email":"any@any.gmail.com","phone":"e6ywwRe4jcqxXfCZOj_1e","id":"vfv2xVl4U"},{"name":"Igor","email":"any@any.gmail.com","phone":"e6ywwRe4jcqxXfCZOj_1e","id":"yqCWk6AOn"},{"name":"Igor","email":"any@any.gmail.com","phone":"e6ywwRe4jcqxXfCZOj_1e","id":"Cw7-IYfle"},{"name":"Igor","email":"any@any.gmail.com","phone":"e6ywwRe4jcqxXfCZOj_1e","id":"bu_WcCDot"},{"name":"Igor","email":"any@any.gmail.com","phone":"e6ywwRe4jcqxXfCZOj_1e","id":"lB_E53VUv"},{"name":"Igor","email":"any@any.gmail.com","phone":"e6ywwRe4jcqxXfCZOj_1e","id":"tptDThKBD"},{"name":"Igor","email":"any@any.gmail.com","phone":"e6ywwRe4jcqxXfCZOj_1e","id":"uE2Nxmusc"},{"name":"Igor","email":"any@any.gmail.com","phone":"e6ywwRe4jcqxXfCZOj_1e","id":"fziSKsDtM"},{"name":"Igor","email":"any@any.gmail.com","phone":"e6ywwRe4jcqxXfCZOj_1e","id":"TluiJWBRy"},{"name":"Igor","email":"any@any.gmail.com","phone":"e6ywwRe4jcqxXfCZOj_1e","id":"BySrl1eKM"},{"name":"Igor","email":"any@any.gmail.com","phone":"e6ywwRe4jcqxXfCZOj_1e","id":"AhuidKemg"},{"name":"Igor","email":"any@any.gmail.com","phone":"e6ywwRe4jcqxXfCZOj_1e","id":"ozyFnJhGK"},{"name":"Igor","email":"any@any.gmail.com","phone":"e6ywwRe4jcqxXfCZOj_1e","id":"U4ABEGLTB"},{"name":"Igor","email":"any@any.gmail.com","phone":"e6ywwRe4jcqxXfCZOj_1e","id":"dZCFvpzBX"},{"name":"Igor","email":"any@any.gmail.com","phone":"e6ywwRe4jcqxXfCZOj_1e","id":"7beMvuO3X"},{"name":"Igor","email":"any@any.gmail.com","phone":"e6ywwRe4jcqxXfCZOj_1e","id":"Nq02ZA9Ho"},{"name":"Igor","email":"any@any.gmail.com","phone":"e6ywwRe4jcqxXfCZOj_1e","id":"OmV0p0vm1"},{"name":"Igor","email":"any@any.gmail.com","phone":"e6ywwRe4jcqxXfCZOj_1e","id":"XYHjpbiqT"},{"name":"Igor","email":"any@any.gmail.com","phone":"e6ywwRe4jcqxXfCZOj_1e","id":"6eRLy3ZnI"},{"name":"Igor","email":"any@any.gmail.com","phone":"e6ywwRe4jcqxXfCZOj_1e","id":"huyBWS7dX"},{"name":"Igor","email":"any@any.gmail.com","phone":"e6ywwRe4jcqxXfCZOj_1e","id":"fUgXluN7Z"},{"name":"Igor","email":"any@any.gmail.com","phone":"e6ywwRe4jcqxXfCZOj_1e","id":"lUKf-gBI2"},{"name":"Igor","email":"any@any.gmail.com","phone":"e6ywwRe4jcqxXfCZOj_1e","id":"XLHZ9er4j"},{"name":"Igor","email":"any@any.gmail.com","phone":"e6ywwRe4jcqxXfCZOj_1e","id":"26LEg-ynv"},{"name":"Igor","email":"any@any.gmail.com","phone":"e6ywwRe4jcqxXfCZOj_1e","id":"6WPZq6kvf"},{"name":"Igor","email":"any@any.gmail.com","phone":"e6ywwRe4jcqxXfCZOj_1e","id":"nMTJH8Y2z"},{"name":"Igor","email":"any@any.gmail.com","phone":"e6ywwRe4jcqxXfCZOj_1e","id":"HG1erLOVb"},{"name":"Igor","email":"any@any.gmail.com","phone":"e6ywwRe4jcqxXfCZOj_1e","id":"IEzVEnJs7"},{"name":"Igor","email":"any@any.gmail.com","phone":"e6ywwRe4jcqxXfCZOj_1e","id":"6o034Nyxo"},{"name":"Igor","email":"any@any.gmail.com","phone":"e6ywwRe4jcqxXfCZOj_1e","id":"z7K1eRbq4"},{"name":"Igor","email":"any@any.gmail.com","phone":"e6ywwRe4jcqxXfCZOj_1e","id":"UKtegnvn2"},{"name":"Igor","email":"any@any.gmail.com","phone":"e6ywwRe4jcqxXfCZOj_1e","id":"Yzbv84R2o"},{"name":"Igor","email":"any@any.gmail.com","phone":"e6ywwRe4jcqxXfCZOj_1e","id":"GEGDC1yF3"},{"name":"Igor","email":"any@any.gmail.com","phone":"e6ywwRe4jcqxXfCZOj_1e","id":"xjEtuqmLU"},{"name":"Igor","email":"any@any.gmail.com","phone":"e6ywwRe4jcqxXfCZOj_1e","id":"8FP3Kfyya"},{"name":"Igor","email":"any@any.gmail.com","phone":"e6ywwRe4jcqxXfCZOj_1e","id":"yJwAvKMpp"},{"name":"Igor","email":"any@any.gmail.com","phone":"e6ywwRe4jcqxXfCZOj_1e","id":"46xJq4Hgl"},{"name":"Igor","email":"any@any.gmail.com","phone":"e6ywwRe4jcqxXfCZOj_1e","id":"Rnw6kJLsq"},{"name":"Igor","email":"any@any.gmail.com","phone":"e6ywwRe4jcqxXfCZOj_1e","id":"7wco1asFp"},{"name":"Igor","email":"any@any.gmail.com","phone":"e6ywwRe4jcqxXfCZOj_1e","id":"FPAbNvpxF"},{"name":"Igor","email":"any@any.gmail.com","phone":"e6ywwRe4jcqxXfCZOj_1e","id":"SpGTMKL_9"},{"name":"Igor","email":"any@any.gmail.com","phone":"e6ywwRe4jcqxXfCZOj_1e","id":"-7lKaOCQQ"},{"name":"Igor","email":"any@any.gmail.com","phone":"e6ywwRe4jcqxXfCZOj_1e","id":"M2JqXJMgm"},{"name":"Igor","email":"any@any.gmail.com","phone":"e6ywwRe4jcqxXfCZOj_1e","id":"Y9HFSmP4y"},{"name":"Igor","email":"any@any.gmail.com","phone":"e6ywwRe4jcqxXfCZOj_1e","id":"JnmpHnnOX"},{"name":"Igor","email":"any@any.gmail.com","phone":"e6ywwRe4jcqxXfCZOj_1e","id":"0lJyqcDMO"},{"name":"Igor","email":"any@any.gmail.com","phone":"e6ywwRe4jcqxXfCZOj_1e","id":"zeRZtgEHn"},{"name":"Igor","email":"any@any.gmail.com","phone":"e6ywwRe4jcqxXfCZOj_1e","id":"9o5bu8AX5"},{"name":"Igor","email":"any@any.gmail.com","phone":"e6ywwRe4jcqxXfCZOj_1e","id":"iMaDu7L3E"},{"name":"Igor","email":"any@any.gmail.com","phone":"e6ywwRe4jcqxXfCZOj_1e","id":"NVsiZrtwC"},{"name":"Igor","email":"any@any.gmail.com","phone":"e6ywwRe4jcqxXfCZOj_1e","id":"w3VoFbK37"},{"name":"Igor","email":"any@any.gmail.com","phone":"e6ywwRe4jcqxXfCZOj_1e","id":"qcB91Eq7j"},{"name":"Igor","email":"any@any.gmail.com","phone":"e6ywwRe4jcqxXfCZOj_1e","id":"F4V68tqSj"},{"name":"Igor","email":"any@any.gmail.com","phone":"e6ywwRe4jcqxXfCZOj_1e","id":"ZepoZ2Ujh"},{"name":"Igor","email":"any@any.gmail.com","phone":"e6ywwRe4jcqxXfCZOj_1e","id":"8xQTZG6hs"},{"name":"Igor","email":"any@any.gmail.com","phone":"e6ywwRe4jcqxXfCZOj_1e","id":"IfKW1g-U0"},{"name":"Igor","email":"any@any.gmail.com","phone":"e6ywwRe4jcqxXfCZOj_1e","id":"DQgFrdkDz"},{"name":"Igor","email":"any@any.gmail.com","phone":"e6ywwRe4jcqxXfCZOj_1e","id":"C2ihYxy1G"},{"name":"Igor","email":"any@any.gmail.com","phone":"e6ywwRe4jcqxXfCZOj_1e","id":"Ga-jZ6ZZk"},{"name":"Igor","email":"any@any.gmail.com","phone":"e6ywwRe4jcqxXfCZOj_1e","id":"FBMiwXa-C"},{"name":"Igor","email":"any@any.gmail.com","phone":"e6ywwRe4jcqxXfCZOj_1e","id":"vIhSpm8TW"},{"name":"Igor","email":"any@any.gmail.com","phone":"e6ywwRe4jcqxXfCZOj_1e","id":"ejua9wH70"},{"name":"Igor","email":"any@any.gmail.com","phone":"e6ywwRe4jcqxXfCZOj_1e","id":"utIznNvuk"},{"name":"Igor","email":"any@any.gmail.com","phone":"e6ywwRe4jcqxXfCZOj_1e","id":"40iF6wOkc"},{"name":"Igor","email":"any@any.gmail.com","phone":"e6ywwRe4jcqxXfCZOj_1e","id":"X3CgV1l-G"},{"name":"Igor","email":"any@any.gmail.com","phone":"e6ywwRe4jcqxXfCZOj_1e","id":"y5l32T8Hg"},{"name":"Igor","email":"any@any.gmail.com","phone":"e6ywwRe4jcqxXfCZOj_1e","id":"j1qa0xpMx"},{"name":"Igor","email":"any@any.gmail.com","phone":"e6ywwRe4jcqxXfCZOj_1e","id":"ErMJcVQLJ"},{"name":"Igor","email":"any@any.gmail.com","phone":"e6ywwRe4jcqxXfCZOj_1e","id":"GhNHOLxgD"},{"name":"Igor","email":"any@any.gmail.com","phone":"e6ywwRe4jcqxXfCZOj_1e","id":"hS5WysN9W"},{"name":"Igor","email":"any@any.gmail.com","phone":"e6ywwRe4jcqxXfCZOj_1e","id":"bplhMFfAB"},{"name":"Igor","email":"any@any.gmail.com","phone":"e6ywwRe4jcqxXfCZOj_1e","id":"MPzvbF1K7"},{"name":"Igor","email":"any@any.gmail.com","phone":"e6ywwRe4jcqxXfCZOj_1e","id":"9n0wzUMTX"},{"name":"Igor","email":"any@any.gmail.com","phone":"e6ywwRe4jcqxXfCZOj_1e","id":"QPAw-Tmiy"},{"name":"Igor","email":"any@any.gmail.com","phone":"e6ywwRe4jcqxXfCZOj_1e","id":"PY5FtaYwO"},{"name":"Igor","email":"any@any.gmail.com","phone":"e6ywwRe4jcqxXfCZOj_1e","id":"RsrxxN7gZ"},{"name":"Igor","email":"any@any.gmail.com","phone":"e6ywwRe4jcqxXfCZOj_1e","id":"TH3b7eSkT"},{"name":"Igor","email":"any@any.gmail.com","phone":"e6ywwRe4jcqxXfCZOj_1e","id":"TFsogWJ5U"},{"name":"Igor","email":"any@any.gmail.com","phone":"e6ywwRe4jcqxXfCZOj_1e","id":"gLOM203Sr"},{"name":"Igor","email":"any@any.gmail.com","phone":"e6ywwRe4jcqxXfCZOj_1e","id":"Y6-yBEvwT"},{"name":"Igor","email":"any@any.gmail.com","phone":"e6ywwRe4jcqxXfCZOj_1e","id":"5NPArSiKr"},{"name":"Igor","email":"any@any.gmail.com","phone":"e6ywwRe4jcqxXfCZOj_1e","id":"-KHswr6Qz"},{"name":"Igor","email":"any@any.gmail.com","phone":"e6ywwRe4jcqxXfCZOj_1e","id":"ZlWjngDzp"},{"name":"Igor","email":"any@any.gmail.com","phone":"e6ywwRe4jcqxXfCZOj_1e","id":"u7v91yk-p"},{"name":"Igor","email":"any@any.gmail.com","phone":"e6ywwRe4jcqxXfCZOj_1e","id":"ZNZIZgGG4"},{"name":"Igor","email":"any@any.gmail.com","phone":"e6ywwRe4jcqxXfCZOj_1e","id":"xr5XT8aKV"},{"name":"Igor","email":"any@any.gmail.com","phone":"e6ywwRe4jcqxXfCZOj_1e","id":"vULQ-K4Tb"},{"name":"Igor","email":"any@any.gmail.com","phone":"e6ywwRe4jcqxXfCZOj_1e","id":"zp_xE8Ude"},{"name":"Igor","email":"any@any.gmail.com","phone":"e6ywwRe4jcqxXfCZOj_1e","id":"7dNARjAz4"},{"name":"Igor","email":"any@any.gmail.com","phone":"e6ywwRe4jcqxXfCZOj_1e","id":"f5sAyXbEy"},{"name":"Igor","email":"any@any.gmail.com","phone":"e6ywwRe4jcqxXfCZOj_1e","id":"uC1DughV-"},{"name":"Igor","email":"any@any.gmail.com","phone":"e6ywwRe4jcqxXfCZOj_1e","id":"zfa3e8PMz"},{"name":"Igor","email":"any@any.gmail.com","phone":"e6ywwRe4jcqxXfCZOj_1e","id":"9gaV41YW1"},{"name":"Igor","email":"any@any.gmail.com","phone":"e6ywwRe4jcqxXfCZOj_1e","id":"kvGH7tO-S"},{"name":"Igor","email":"any@any.gmail.com","phone":"e6ywwRe4jcqxXfCZOj_1e","id":"jt3N7COnk"},{"name":"Igor","email":"any@any.gmail.com","phone":"e6ywwRe4jcqxXfCZOj_1e","id":"aw7y3ObC_"},{"name":"Igor","email":"any@any.gmail.com","phone":"e6ywwRe4jcqxXfCZOj_1e","id":"NLfytNJoz"},{"name":"Igor","email":"any@any.gmail.com","phone":"e6ywwRe4jcqxXfCZOj_1e","id":"KJLO2Uj9c"},{"name":"Igor","email":"any@any.gmail.com","phone":"e6ywwRe4jcqxXfCZOj_1e","id":"KMRTmdRqK"},{"name":"Igor","email":"any@any.gmail.com","phone":"e6ywwRe4jcqxXfCZOj_1e","id":"pz47rQR7t"},{"name":"Igor","email":"any@any.gmail.com","phone":"e6ywwRe4jcqxXfCZOj_1e","id":"dDWBW0n__"},{"name":"Igor","email":"any@any.gmail.com","phone":"e6ywwRe4jcqxXfCZOj_1e","id":"V76gj_Qqu"},{"name":"Igor","email":"any@any.gmail.com","phone":"e6ywwRe4jcqxXfCZOj_1e","id":"88Y4HYcCe"},{"name":"Igor","email":"any@any.gmail.com","phone":"e6ywwRe4jcqxXfCZOj_1e","id":"6rrk8cdl1"},{"name":"Igor","email":"any@any.gmail.com","phone":"e6ywwRe4jcqxXfCZOj_1e","id":"ADs11saSU"},{"name":"Igor","email":"any@any.gmail.com","phone":"e6ywwRe4jcqxXfCZOj_1e","id":"blsSASYf_"},{"name":"Igor","email":"any@any.gmail.com","phone":"e6ywwRe4jcqxXfCZOj_1e","id":"P_PpQvnZu"},{"name":"Igor","email":"any@any.gmail.com","phone":"e6ywwRe4jcqxXfCZOj_1e","id":"SH0Rlnw_Y"},{"name":"Igor","email":"any@any.gmail.com","phone":"e6ywwRe4jcqxXfCZOj_1e","id":"Pflu6J88p"},{"name":"Igor","email":"any@any.gmail.com","phone":"e6ywwRe4jcqxXfCZOj_1e","id":"142GnoJo5"},{"name":"Igor","email":"any@any.gmail.com","phone":"e6ywwRe4jcqxXfCZOj_1e","id":"kEkBGlfx3"},{"name":"Igor","email":"any@any.gmail.com","phone":"e6ywwRe4jcqxXfCZOj_1e","id":"C7ztawB5V"},{"name":"Igor","email":"any@any.gmail.com","phone":"e6ywwRe4jcqxXfCZOj_1e","id":"K3kCovBN2"},{"name":"Igor","email":"any@any.gmail.com","phone":"e6ywwRe4jcqxXfCZOj_1e","id":"LXI5s4Zvr"},{"name":"Igor","email":"any@any.gmail.com","phone":"e6ywwRe4jcqxXfCZOj_1e","id":"qkQq5YA6O"},{"name":"Igor","email":"any@any.gmail.com","phone":"e6ywwRe4jcqxXfCZOj_1e","id":"5XGSaLoI1"},{"name":"Igor","email":"any@any.gmail.com","phone":"e6ywwRe4jcqxXfCZOj_1e","id":"G6VBjl02t"},{"name":"Igor","email":"any@any.gmail.com","phone":"e6ywwRe4jcqxXfCZOj_1e","id":"YwzMyjmWh"},{"name":"Igor","email":"any@any.gmail.com","phone":"e6ywwRe4jcqxXfCZOj_1e","id":"FDF2oF3n7"},{"name":"Igor","email":"any@any.gmail.com","phone":"e6ywwRe4jcqxXfCZOj_1e","id":"VGE2CWO9z"},{"name":"Igor","email":"any@any.gmail.com","phone":"e6ywwRe4jcqxXfCZOj_1e","id":"iSMy7Hcjx"},{"name":"Igor","email":"any@any.gmail.com","phone":"e6ywwRe4jcqxXfCZOj_1e","id":"fLfQYpkkk"},{"name":"Igor","email":"any@any.gmail.com","phone":"e6ywwRe4jcqxXfCZOj_1e","id":"tTXJ3TT3K"},{"name":"Igor","email":"any@any.gmail.com","phone":"e6ywwRe4jcqxXfCZOj_1e","id":"2ezguc5Dn"},{"name":"Igor","email":"any@any.gmail.com","phone":"e6ywwRe4jcqxXfCZOj_1e","id":"gFrUqCbK2"},{"name":"Igor","email":"any@any.gmail.com","phone":"e6ywwRe4jcqxXfCZOj_1e","id":"wWhCrk03n"},{"name":"Igor","email":"any@any.gmail.com","phone":"e6ywwRe4jcqxXfCZOj_1e","id":"3j_r-VMZf"},{"name":"Igor","email":"any@any.gmail.com","phone":"e6ywwRe4jcqxXfCZOj_1e","id":"TKXLdP5qE"},{"name":"Igor","email":"any@any.gmail.com","phone":"e6ywwRe4jcqxXfCZOj_1e","id":"SuJcwYQ6r"},{"name":"Igor","email":"any@any.gmail.com","phone":"e6ywwRe4jcqxXfCZOj_1e","id":"qP22mtzz9"},{"name":"Igor","email":"any@any.gmail.com","phone":"e6ywwRe4jcqxXfCZOj_1e","id":"Ad77RZZQd"},{"name":"Igor","email":"any@any.gmail.com","phone":"e6ywwRe4jcqxXfCZOj_1e","id":"nbMqyI1FQ"},{"name":"Igor","email":"any@any.gmail.com","phone":"e6ywwRe4jcqxXfCZOj_1e","id":"qHXLyDU4B"},{"name":"Igor","email":"any@any.gmail.com","phone":"e6ywwRe4jcqxXfCZOj_1e","id":"4F4HpWLVr"},{"name":"Igor","email":"any@any.gmail.com","phone":"e6ywwRe4jcqxXfCZOj_1e","id":"bksmVqNI7"},{"name":"Igor","email":"any@any.gmail.com","phone":"e6ywwRe4jcqxXfCZOj_1e","id":"uRrMqzVWx"},{"name":"Igor","email":"any@any.gmail.com","phone":"e6ywwRe4jcqxXfCZOj_1e","id":"9HsJTprND"},{"name":"Igor","email":"any@any.gmail.com","phone":"e6ywwRe4jcqxXfCZOj_1e","id":"dLRfhitad"},{"name":"Igor","email":"any@any.gmail.com","phone":"e6ywwRe4jcqxXfCZOj_1e","id":"Px0NQzmkR"},{"name":"Igor","email":"any@any.gmail.com","phone":"e6ywwRe4jcqxXfCZOj_1e","id":"1Fvj2aWVB"},{"name":"Igor","email":"any@any.gmail.com","phone":"e6ywwRe4jcqxXfCZOj_1e","id":"rLi_FtW9C"},{"name":"Igor","email":"any@any.gmail.com","phone":"e6ywwRe4jcqxXfCZOj_1e","id":"vMyHcpnef"},{"name":"Igor","email":"any@any.gmail.com","phone":"e6ywwRe4jcqxXfCZOj_1e","id":"OVGtWnDZ5"},{"name":"Igor","email":"any@any.gmail.com","phone":"e6ywwRe4jcqxXfCZOj_1e","id":"6UyTcQPbj"},{"name":"Igor","email":"any@any.gmail.com","phone":"e6ywwRe4jcqxXfCZOj_1e","id":"f4WcKbGLT"},{"name":"Igor","email":"any@any.gmail.com","phone":"e6ywwRe4jcqxXfCZOj_1e","id":"ldDixxDJ2"},{"name":"Igor","email":"any@any.gmail.com","phone":"e6ywwRe4jcqxXfCZOj_1e","id":"Or8pVqCPY"},{"name":"Igor","email":"any@any.gmail.com","phone":"e6ywwRe4jcqxXfCZOj_1e","id":"KqcZABUfo"},{"name":"Igor","email":"any@any.gmail.com","phone":"e6ywwRe4jcqxXfCZOj_1e","id":"aJF3b4hWw"},{"name":"Igor","email":"any@any.gmail.com","phone":"e6ywwRe4jcqxXfCZOj_1e","id":"MA5X_X66O"},{"name":"Igor","email":"any@any.gmail.com","phone":"e6ywwRe4jcqxXfCZOj_1e","id":"j6bEE0XPc"},{"name":"Igor","email":"any@any.gmail.com","phone":"e6ywwRe4jcqxXfCZOj_1e","id":"Ntyt29wRD"},{"name":"Igor","email":"any@any.gmail.com","phone":"e6ywwRe4jcqxXfCZOj_1e","id":"14pcmDaRN"},{"name":"Igor","email":"any@any.gmail.com","phone":"e6ywwRe4jcqxXfCZOj_1e","id":"zcucY-0Zh"},{"name":"Igor","email":"any@any.gmail.com","phone":"e6ywwRe4jcqxXfCZOj_1e","id":"QfxI1cmbi"},{"name":"Igor","email":"any@any.gmail.com","phone":"e6ywwRe4jcqxXfCZOj_1e","id":"PurkW1tMk"},{"name":"Igor","email":"any@any.gmail.com","phone":"e6ywwRe4jcqxXfCZOj_1e","id":"FrXviB7lU"},{"name":"Igor","email":"any@any.gmail.com","phone":"e6ywwRe4jcqxXfCZOj_1e","id":"vZSphPG4Y"},{"name":"Igor","email":"any@any.gmail.com","phone":"e6ywwRe4jcqxXfCZOj_1e","id":"08IXya5lk"},{"name":"Igor","email":"any@any.gmail.com","phone":"e6ywwRe4jcqxXfCZOj_1e","id":"HTLMZ-WZ3"},{"name":"Igor","email":"any@any.gmail.com","phone":"e6ywwRe4jcqxXfCZOj_1e","id":"WhD0wVL2L"},{"name":"Igor","email":"any@any.gmail.com","phone":"e6ywwRe4jcqxXfCZOj_1e","id":"K3k5suDBV"},{"name":"Igor","email":"any@any.gmail.com","phone":"e6ywwRe4jcqxXfCZOj_1e","id":"8yuEwmTAB"},{"name":"Igor","email":"any@any.gmail.com","phone":"e6ywwRe4jcqxXfCZOj_1e","id":"1tODJstDe"},{"name":"Igor","email":"any@any.gmail.com","phone":"e6ywwRe4jcqxXfCZOj_1e","id":"v8QW2P73w"},{"name":"Igor","email":"any@any.gmail.com","phone":"e6ywwRe4jcqxXfCZOj_1e","id":"jh6X1e-ZY"},{"name":"Igor","email":"any@any.gmail.com","phone":"e6ywwRe4jcqxXfCZOj_1e","id":"Mdf3ojxYc"},{"name":"Igor","email":"any@any.gmail.com","phone":"e6ywwRe4jcqxXfCZOj_1e","id":"3x-ilOQ73"}]